module_name/__init__.py
module_name/main.py
Name_factor-1.0.0.dist-info/LICENSE
Name_factor-1.0.0.dist-info/METADATA
Name_factor-1.0.0.dist-info/WHEEL
Name_factor-1.0.0.dist-info/top_level.txt
Name_factor-1.0.0.dist-info/zip-safe
Name_factor-1.0.0.dist-info/RECORD
