Metadata-Version: 2.1
Name: Name-factor
Version: 1.0.0
Summary: Module description.
Home-page: https://www.discordapp.com/users/771212911606628363
Author: Author's name
Author-email: devpsingh2020@gmail.com
License: GNU General Public License v3 (GPLv3)
Platform: UNKNOWN
Classifier: Programming Language :: Python :: 3
Classifier: License :: OSI Approved :: GNU General Public License v3 (GPLv3)
Classifier: Operating System :: OS Independent
Requires-Python: >=3.0
License-File: LICENSE
